fluentcms_filer/__init__.py
fluentcms_filer/file/__init__.py
fluentcms_filer/file/content_plugins.py
fluentcms_filer/file/models.py
fluentcms_filer/file/tests.py
fluentcms_filer/file/locale/ru/LC_MESSAGES/django.mo
fluentcms_filer/file/locale/ru/LC_MESSAGES/django.po
fluentcms_filer/file/migrations/0001_initial.py
fluentcms_filer/file/migrations/__init__.py
fluentcms_filer/file/static/fluentcms_filer/file/admin.css
fluentcms_filer/file/templates/admin/fluentcms_filer/file/admin_form.html
fluentcms_filer/file/templates/admin/fluentcms_filer/file/admin_init.html
fluentcms_filer/file/templates/fluentcms_filer/file.html
fluentcms_filer/picture/__init__.py
fluentcms_filer/picture/content_plugins.py
fluentcms_filer/picture/models.py
fluentcms_filer/picture/tests.py
fluentcms_filer/picture/locale/ru/LC_MESSAGES/django.mo
fluentcms_filer/picture/locale/ru/LC_MESSAGES/django.po
fluentcms_filer/picture/migrations/0001_initial.py
fluentcms_filer/picture/migrations/__init__.py
fluentcms_filer/picture/static/fluentcms_filer/picture/admin.css
fluentcms_filer/picture/templates/admin/fluentcms_filer/picture/admin_form.html
fluentcms_filer/picture/templates/admin/fluentcms_filer/picture/admin_init.html
fluentcms_filer/picture/templates/fluentcms_filer/picture.html
fluentcms_filer/teaser/__init__.py
fluentcms_filer/teaser/content_plugins.py
fluentcms_filer/teaser/models.py
fluentcms_filer/teaser/tests.py
fluentcms_filer/teaser/locale/ru/LC_MESSAGES/django.mo
fluentcms_filer/teaser/locale/ru/LC_MESSAGES/django.po
fluentcms_filer/teaser/migrations/0001_initial.py
fluentcms_filer/teaser/migrations/0002_auto_20150924_0221.py
fluentcms_filer/teaser/migrations/0003_auto_20211121_0537.py
fluentcms_filer/teaser/migrations/__init__.py
fluentcms_filer/teaser/static/fluentcms_filer/teaser/admin.css
fluentcms_filer/teaser/templates/admin/fluentcms_filer/teaser/admin_form.html
fluentcms_filer/teaser/templates/admin/fluentcms_filer/teaser/admin_init.html
fluentcms_filer-2.0.1.dist-info/AUTHORS
fluentcms_filer-2.0.1.dist-info/LICENSE
fluentcms_filer-2.0.1.dist-info/METADATA
fluentcms_filer-2.0.1.dist-info/WHEEL
fluentcms_filer-2.0.1.dist-info/top_level.txt
fluentcms_filer-2.0.1.dist-info/RECORD
